{
  "Passing Leaders": [
    {
      "RK": "1",
      "NAME": "Carson Beck, QB",
      "TEAM": "MIA",
      "RESULT": "W34-17atVT",
      "COMP": "27",
      "ATT": "32",
      "YDS": "320",
      "TD": "4",
      "INT": "0",
      "RAT": "209.6"
    },
    {
      "RK": "2",
      "NAME": "Preston Stone, QB",
      "TEAM": "NU",
      "RESULT": "W38-35vs.MINN",
      "COMP": "25",
      "ATT": "30",
      "YDS": "305",
      "TD": "2",
      "INT": "0",
      "RAT": "190.7"
    },
    {
      "RK": "3",
      "NAME": "Ta'Quan Roberson, QB",
      "TEAM": "BUF",
      "RESULT": "L20-37vs.M-OH",
      "COMP": "24",
      "ATT": "48",
      "YDS": "303",
      "TD": "2",
      "INT": "2",
      "RAT": "108.4"
    },
    {
      "RK": "",
      "NAME": "Kevin Jennings, QB",
      "TEAM": "SMU",
      "RESULT": "W38-6vs.LOU",
      "COMP": "29",
      "ATT": "37",
      "YDS": "303",
      "TD": "3",
      "INT": "0",
      "RAT": "173.9"
    },
    {
      "RK": "5",
      "NAME": "Robby Ashford, QB",
      "TEAM": "WAKE",
      "RESULT": "W52-14vs.DEL",
      "COMP": "15",
      "ATT": "22",
      "YDS": "292",
      "TD": "3",
      "INT": "1",
      "RAT": "215.6"
    },
    {
      "RK": "6",
      "NAME": "Baylor Hayes, QB",
      "TEAM": "TLSA",
      "RESULT": "W26-25atARMY",
      "COMP": "20",
      "ATT": "31",
      "YDS": "267",
      "TD": "1",
      "INT": "0",
      "RAT": "147.5"
    },
    {
      "RK": "7",
      "NAME": "Drake Lindsey, QB",
      "TEAM": "MINN",
      "RESULT": "L35-38atNU",
      "COMP": "20",
      "ATT": "30",
      "YDS": "264",
      "TD": "4",
      "INT": "0",
      "RAT": "184.6"
    },
    {
      "RK": "8",
      "NAME": "Jaylen Raynor, QB",
      "TEAM": "ARST",
      "RESULT": "L30-34vs.UL",
      "COMP": "25",
      "ATT": "43",
      "YDS": "256",
      "TD": "0",
      "INT": "0",
      "RAT": "108.1"
    },
    {
      "RK": "9",
      "NAME": "Anthony Colandrea, QB",
      "TEAM": "UNLV",
      "RESULT": "W38-10vs.HAW",
      "COMP": "21",
      "ATT": "26",
      "YDS": "253",
      "TD": "3",
      "INT": "0",
      "RAT": "200.6"
    },
    {
      "RK": "10",
      "NAME": "Rocco Becht, QB",
      "TEAM": "ISU",
      "RESULT": "W38-14vs.KU",
      "COMP": "18",
      "ATT": "23",
      "YDS": "241",
      "TD": "3",
      "INT": "0",
      "RAT": "209.3"
    }
  ],
  "Rushing Leaders": [
    {
      "RK": "1",
      "NAME": "Dominic Richardson, RB",
      "TEAM": "TLSA",
      "RESULT": "W26-25atARMY",
      "CAR": "28",
      "YDS": "203",
      "YPC": "7.3",
      "TD": "1"
    },
    {
      "RK": "2",
      "NAME": "Sieh Bangura, RB",
      "TEAM": "OHIO",
      "RESULT": "W42-14vs.MASS",
      "CAR": "27",
      "YDS": "196",
      "YPC": "7.3",
      "TD": "2"
    },
    {
      "RK": "3",
      "NAME": "Colton Joseph, QB",
      "TEAM": "ODU",
      "RESULT": "",
      "CAR": "20",
      "YDS": "189",
      "YPC": "9.5",
      "TD": "1"
    },
    {
      "RK": "4",
      "NAME": "Deuce Knight, QB",
      "TEAM": "AUB",
      "RESULT": "",
      "CAR": "6",
      "YDS": "173",
      "YPC": "28.8",
      "TD": "4"
    },
    {
      "RK": "5",
      "NAME": "Cale Hellums, QB",
      "TEAM": "ARMY",
      "RESULT": "L25-26vs.TLSA",
      "CAR": "32",
      "YDS": "159",
      "YPC": "5.0",
      "TD": "3"
    },
    {
      "RK": "6",
      "NAME": "Jalen Buckley, RB",
      "TEAM": "WMU",
      "RESULT": "W35-19atNIU",
      "CAR": "24",
      "YDS": "133",
      "YPC": "5.5",
      "TD": "2"
    },
    {
      "RK": "7",
      "NAME": "Chip Trayanum, RB",
      "TEAM": "TOL",
      "RESULT": "",
      "CAR": "13",
      "YDS": "131",
      "YPC": "10.1",
      "TD": "1"
    },
    {
      "RK": "8",
      "NAME": "Caleb Komolafe, RB",
      "TEAM": "NU",
      "RESULT": "W38-35vs.MINN",
      "CAR": "22",
      "YDS": "129",
      "YPC": "5.9",
      "TD": "1"
    },
    {
      "RK": "9",
      "NAME": "Wayne Knight, RB",
      "TEAM": "JMU",
      "RESULT": "",
      "CAR": "15",
      "YDS": "126",
      "YPC": "8.4",
      "TD": "1"
    },
    {
      "RK": "10",
      "NAME": "Jordan Brunson, RB",
      "TEAM": "M-OH",
      "RESULT": "W37-20atBUF",
      "CAR": "16",
      "YDS": "123",
      "YPC": "7.7",
      "TD": "0"
    }
  ],
  "Receiving Leaders": [
    {
      "RK": "1",
      "NAME": "Carlos Hernandez, WR",
      "TEAM": "WAKE",
      "RESULT": "W52-14vs.DEL",
      "REC": "5",
      "YDS": "197",
      "YPR": "39.4",
      "TD": "2"
    },
    {
      "RK": "2",
      "NAME": "Malcolm Simmons, WR",
      "TEAM": "AUB",
      "RESULT": "",
      "REC": "5",
      "YDS": "149",
      "YPR": "29.8",
      "TD": "1"
    },
    {
      "RK": "3",
      "NAME": "Nik McMillan, WR",
      "TEAM": "BUF",
      "RESULT": "L20-37vs.M-OH",
      "REC": "8",
      "YDS": "147",
      "YPR": "18.4",
      "TD": "0"
    },
    {
      "RK": "4",
      "NAME": "Malachi Toney, WR",
      "TEAM": "MIA",
      "RESULT": "W34-17atVT",
      "REC": "12",
      "YDS": "146",
      "YPR": "12.2",
      "TD": "1"
    },
    {
      "RK": "5",
      "NAME": "Kris Hutson, WR",
      "TEAM": "ARIZ",
      "RESULT": "W41-17vs.BAY",
      "REC": "9",
      "YDS": "133",
      "YPR": "14.8",
      "TD": "1"
    },
    {
      "RK": "6",
      "NAME": "Hayden Eligon II, WR",
      "TEAM": "NU",
      "RESULT": "W38-35vs.MINN",
      "REC": "7",
      "YDS": "127",
      "YPR": "18.1",
      "TD": "0"
    },
    {
      "RK": "7",
      "NAME": "Corey Rucker, WR",
      "TEAM": "ARST",
      "RESULT": "L30-34vs.UL",
      "REC": "8",
      "YDS": "120",
      "YPR": "15.0",
      "TD": "0"
    },
    {
      "RK": "8",
      "NAME": "Kevin Coleman Jr., WR",
      "TEAM": "MIZ",
      "RESULT": "L6-17atOU",
      "REC": "7",
      "YDS": "115",
      "YPR": "16.4",
      "TD": "0"
    },
    {
      "RK": "9",
      "NAME": "Victor Snow, WR",
      "TEAM": "BUF",
      "RESULT": "L20-37vs.M-OH",
      "REC": "9",
      "YDS": "111",
      "YPR": "12.3",
      "TD": "1"
    },
    {
      "RK": "",
      "NAME": "Griffin Wilde, WR",
      "TEAM": "NU",
      "RESULT": "W38-35vs.MINN",
      "REC": "11",
      "YDS": "111",
      "YPR": "10.1",
      "TD": "1"
    }
  ]
}